LICENSE
MANIFEST.in
README.rst
setup.cfg
setup.py
tinyfasta/__init__.py
tinyfasta.egg-info/PKG-INFO
tinyfasta.egg-info/SOURCES.txt
tinyfasta.egg-info/dependency_links.txt
tinyfasta.egg-info/top_level.txt