Metadata-Version: 1.1
Name: tinyfasta
Version: 0.1.0
Summary: Tiny FASTA package, without dependencies, for processing biological sequence files.
Home-page: https://github.com/tjelvar-olsson/tinyfasta
Author: Tjelvar Olsson
Author-email: tjelvar.olsson@gmail.com
License: MIT
Download-URL: https://github.com/tjelvar-olsson/tinyfasta/0.1.0
Keywords: fasta,bioinformatics
Platform: UNKNOWN
Classifier: Development Status :: 3 - Alpha
Classifier: Intended Audience :: Developers
Classifier: Intended Audience :: Science/Research
Classifier: License :: OSI Approved :: MIT License
Classifier: Natural Language :: English
Classifier: Programming Language :: Python
Classifier: Programming Language :: Python :: 2
Classifier: Programming Language :: Python :: 2.7
Classifier: Programming Language :: Python :: 3
Classifier: Programming Language :: Python :: 3.2
Classifier: Programming Language :: Python :: 3.3
Classifier: Programming Language :: Python :: 3.4
Classifier: Topic :: Scientific/Engineering
Classifier: Topic :: Scientific/Engineering :: Bio-Informatics
